LCSFinder.py
_LCSFinder.pypy37-pp73-x86-linux-gnu.so
LCSFinder-0.5.0.data/headers/LCSFinder.h
LCSFinder-0.5.0.dist-info/METADATA
LCSFinder-0.5.0.dist-info/WHEEL
LCSFinder-0.5.0.dist-info/top_level.txt
LCSFinder-0.5.0.dist-info/RECORD
LCSFinder-0.5.0.dist-info/LICENSE.md
