Metadata-Version: 2.1
Name: LCSFinder
Version: 0.5.0
Summary: A toolkit for quickly calculating longest common substrings with specific relevance to entropy estimation.
Home-page: https://github.com/bridget-smart/LCSFinder
Author: Bridget Smart and Max Ward
Author-email: bridget.anna.smart@gmail.com
License: MIT license
License-File: LICENSE.md
